<?xml version="1.0" encoding="UTF-8"?>
<metadata xml:lang="en"><Esri><CreaDate>20150608</CreaDate><CreaTime>12544700</CreaTime><ArcGISFormat>1.0</ArcGISFormat><ArcGISstyle>Item Description</ArcGISstyle><SyncOnce>TRUE</SyncOnce><DataProperties><itemProps><itemLocation><linkage Sync="TRUE">file://\\psf\Parallels-Share\GEOMAR\Shapes\Permissive Areas\Nodules_Hein2013</linkage><protocol Sync="TRUE">Local Area Network</protocol></itemLocation></itemProps><copyHistory><copy source="X:\GEOMAR\DG-MaritimeAffairs&amp; Fisheries-STUDY\shapes\28_05_2014\Nodules_Hein2013" dest="\\psf\Parallels-Share\GEOMAR\Shapes\Permissive Areas\Nodules_Hein2013" date="20150608" time="12544700"></copy></copyHistory></DataProperties></Esri></metadata>
